robloxFunctions/Exceptions.py
robloxFunctions/Followers.py
robloxFunctions/Friends.py
robloxFunctions/Games.py
robloxFunctions/Groups.py
robloxFunctions/Inventory.py
robloxFunctions/Users.py
robloxFunctions/__init__.py
robloxFunctions-0.1.9.dist-info/METADATA
robloxFunctions-0.1.9.dist-info/WHEEL
robloxFunctions-0.1.9.dist-info/top_level.txt
robloxFunctions-0.1.9.dist-info/RECORD
