Metadata-Version: 2.1
Name: robloxFunctions
Version: 0.1.9
Summary: A python package that uses roblox's API.
Home-page: https://github.com/Zach-Tolentino-161/robloxFunctions/tree/master
Author: PandaGamerYT
Author-email: zachgameryt08@gmail.com
License: MIT
Platform: UNKNOWN
Requires-Python: >=3.8
Requires-Dist: requests
